tx2/__init__.py
tx2/cache.py
tx2/calc.py
tx2/dashboard.py
tx2/dataset.py
tx2/utils.py
tx2/visualization.py
tx2/wrapper.py
tx2-1.3.1.dist-info/LICENSE
tx2-1.3.1.dist-info/METADATA
tx2-1.3.1.dist-info/WHEEL
tx2-1.3.1.dist-info/top_level.txt
tx2-1.3.1.dist-info/RECORD
