Metadata-Version: 2.1
Name: tx2
Version: 1.3.1
Summary: Transformer eXplainability and eXploration
Home-page: https://github.com/ORNL/tx2
Author: Nathan Martindale, Scott L. Stewart
Author-email: tx2-help@ornl.gov
Project-URL: Documentation, https://ornl.github.io/tx2/
Classifier: Programming Language :: Python :: 3
Classifier: License :: OSI Approved :: BSD License
Classifier: Operating System :: OS Independent
Requires-Python: >=3.9
License-File: LICENSE
Requires-Dist: scikit-learn
Requires-Dist: pandas
Requires-Dist: numpy
Requires-Dist: torch
Requires-Dist: tqdm
Requires-Dist: umap-learn
Requires-Dist: matplotlib
Requires-Dist: ipywidgets
Requires-Dist: wordcloud
